<?xml version="1.0" encoding="UTF-8"?>
<!DOCTYPE mapper
PUBLIC "-//mybatis.org//DTD Mapper 3.0//EN"
"http://mybatis.org/dtd/mybatis-3-mapper.dtd">

<mapper namespace="com.koreait.mybatis2.dao.SimpleDao">

	<select id="simpleList" resultType="com.koreait.mybatis2.dto.SimpleDto">
		SELECT *
		  FROM SIMPLE
	</select>
	
	<select id="totalCount" resultType="int">
		SELECT COUNT(*)
		  FROM SIMPLE
	</select>
	<!-- dao이름 -->
	<insert id="simpleInsert">
		INSERT INTO
			SIMPLE (NO, WRITER, TITLE, CONTENT, REGDATE) 
			VALUES(SIMPLE_SEQ.NEXTVAL, #{param1}, #{param2}, #{param3}, SYSDATE)
	</insert>
	
	<select id="simpleView" parameterType="int"  resultType="com.koreait.mybatis2.dto.SimpleDto">
		SELECT * FROM SIMPLE WHERE NO = #{no} 
	</select> <!-- ${no}도 가능함 but 숫자라고 $쓸필요는 없다. -->
	
</mapper>